img_splicer/__init__.py
img_splicer/resources.py
img_splicer/utils.py
img_splicer/static/__init__.py
img_splicer/static/images/__init__.py
img_splicer/static/images/apple32.png
img_splicer/static/images/apple64.png
img_splicer/static/images/linux32.png
img_splicer/static/images/linux64.png
img_splicer/static/images/python32.png
img_splicer/static/images/python64.png
img_splicer-2.0.6.dist-info/licenses/LICENSE
img_splicer-2.0.6.dist-info/METADATA
img_splicer-2.0.6.dist-info/WHEEL
img_splicer-2.0.6.dist-info/top_level.txt
img_splicer-2.0.6.dist-info/RECORD
