Metadata-Version: 2.4
Name: img-splicer
Version: 2.0.6
Summary: img-splicer
Home-page: https://github.com/Hedroed/png-parser
Download-URL: https://github.com/Hedroed/png-parser
Author: Nathan Rydin
Author-email: nrydin@alvinnet.com
Project-URL: Documentation, https://github.com/Hedroed/png-parser
License-File: LICENSE
Dynamic: author
Dynamic: author-email
Dynamic: description
Dynamic: description-content-type
Dynamic: download-url
Dynamic: home-page
Dynamic: license-file
Dynamic: project-url
Dynamic: summary
